PyAwsHelper/__init__.py
PyAwsHelper/boto_helper.py
PyAwsHelper/boto_session.py
PyAwsHelper/region.py
tests/__init__.py
tests/region/__init__.py
tests/region/test_region.py
PyAwsHelper-0.0.10.dist-info/LICENSE
PyAwsHelper-0.0.10.dist-info/METADATA
PyAwsHelper-0.0.10.dist-info/WHEEL
PyAwsHelper-0.0.10.dist-info/top_level.txt
PyAwsHelper-0.0.10.dist-info/RECORD
