Metadata-Version: 2.1
Name: PyAwsHelper
Version: 0.0.10
Summary: Python AWS Helper Library
Home-page: https://github.com/pritul95/PyAwsHelper
Author: Ritul Patel
Author-email: author@example.com
Classifier: Programming Language :: Python :: 3
Classifier: License :: OSI Approved :: MIT License
Classifier: Operating System :: OS Independent
Requires-Python: >=3.6
License-File: LICENSE
Requires-Dist: boto3 >1.8.0
